pyenvapi/__init__.py
pyenvapi/api.py
pyenvapi/exceptions.py
tests/__init__.py
tests/test_api.py
pyenv_api-1.1.0.dist-info/LICENSE
pyenv_api-1.1.0.dist-info/METADATA
pyenv_api-1.1.0.dist-info/WHEEL
pyenv_api-1.1.0.dist-info/top_level.txt
pyenv_api-1.1.0.dist-info/RECORD
