Metadata-Version: 2.1
Name: pyenv-api
Version: 1.1.0
Summary: A simple API for pyenv
Home-page: https://github.com/ulacioh/pyenv-api
Author: Hector Ulacio
Author-email: hectorulacior@gmail.com
License: MIT
Keywords: pyenv,version-management
Platform: UNKNOWN
Classifier: Intended Audience :: Developers
Classifier: License :: OSI Approved :: MIT License
Classifier: Operating System :: Unix
Classifier: Programming Language :: Python
Classifier: Programming Language :: Python :: 3
Classifier: Programming Language :: Python :: 3.6
Classifier: Programming Language :: Python :: 3.7
Classifier: Programming Language :: Python :: 3.8
